ppocronnx/__init__.py
ppocronnx/predict_system.py
ppocronnx/utility.py
ppocronnx/cls/__init__.py
ppocronnx/cls/postprocess.py
ppocronnx/cls/predict_cls.py
ppocronnx/det/__init__.py
ppocronnx/det/postprocess.py
ppocronnx/det/predict_det.py
ppocronnx/det/preprocess.py
ppocronnx/model/ch_PP-OCRv3_det_infer.onnx
ppocronnx/model/ch_PP-OCRv3_rec_infer.onnx
ppocronnx/model/ch_ppocr_mobile_v2.0_cls_infer_model.onnx
ppocronnx/model/ppocr_keys_v1.txt
ppocronnx/rec/__init__.py
ppocronnx/rec/predict_rec.py
ppocronnx/rec/rec_decoder.py
v_ppocr_onnx-0.0.4.1.dist-info/LICENSE
v_ppocr_onnx-0.0.4.1.dist-info/METADATA
v_ppocr_onnx-0.0.4.1.dist-info/WHEEL
v_ppocr_onnx-0.0.4.1.dist-info/top_level.txt
v_ppocr_onnx-0.0.4.1.dist-info/RECORD
