Metadata-Version: 2.1
Name: v-ppocr-onnx
Version: 0.0.4.1
Summary: 利用 onnxruntime 及 PaddleOCR 提供的模型, 对图片中的文字进行检测与识别.
Home-page: https://github.com/triwinds/ppocr-onnx
Author: triwinds
Author-email: triwinds@foxmail.com
License: Apache 2.0
Platform: UNKNOWN
Classifier: Development Status :: 4 - Beta
Classifier: Operating System :: OS Independent
Classifier: Intended Audience :: Developers
Classifier: License :: OSI Approved :: Apache Software License
Classifier: Programming Language :: Python :: 3
Classifier: Topic :: Scientific/Engineering :: Artificial Intelligence
Requires-Dist: onnxruntime-gpu
Requires-Dist: numpy
Requires-Dist: requests
Requires-Dist: opencv-python-headless
Requires-Dist: shapely
Requires-Dist: pyclipper
Requires-Dist: Pillow
